<?xml version="1.0"?>
<!--<!DOCTYPE metadata SYSTEM "http://www.esri.com/metadata/esriprof80.dtd">-->
<metadata xml:lang="en"><Esri><CreaDate>20181018</CreaDate><CreaTime>14442000</CreaTime><SyncOnce>TRUE</SyncOnce><DataProperties><lineage><Process Name="Merge_2" ToolSource="C:\Program Files\ArcGIS\ArcToolbox\Toolboxes\Data Management Tools.tbx\Merge" Date="20071003" Time="153953">Merge C:\ddrive\alaska\Shapefiles_UTM_Zone5\Final_interpretations\Homer_dense_sg2.shp;C:\ddrive\alaska\DVD_Files\Kachemak_interpretations.shp C:\ddrive\alaska\DVD_Files\Kachemak_Interpretations2.shp "Id Id true false false 6 Long 0 6 ,First,#,C:\ddrive\alaska\Shapefiles_UTM_Zone5\Final_interpretations\Homer_dense_sg2.shp,Id,-1,-1,C:\ddrive\alaska\DVD_Files\Kachemak_interpretations.shp,Id,-1,-1;hab_code hab_code true false false 4 Short 0 4 ,First,#,C:\ddrive\alaska\Shapefiles_UTM_Zone5\Final_interpretations\Homer_dense_sg2.shp,hab_code,-1,-1,C:\ddrive\alaska\DVD_Files\Kachemak_interpretations.shp,hab_code,-1,-1;AREA AREA true false false 19 Double 11 18 ,First,#,C:\ddrive\alaska\Shapefiles_UTM_Zone5\Final_interpretations\Homer_dense_sg2.shp,AREA,-1,-1,C:\ddrive\alaska\DVD_Files\Kachemak_interpretations.shp,AREA,-1,-1;hectares hectares true false false 13 Float 11 12 ,First,#,C:\ddrive\alaska\Shapefiles_UTM_Zone5\Final_interpretations\Homer_dense_sg2.shp,hectares,-1,-1,C:\ddrive\alaska\DVD_Files\Kachemak_interpretations.shp,hectares,-1,-1;hab_class hab_class true false false 50 Text 0 0 ,First,#,C:\ddrive\alaska\DVD_Files\Kachemak_interpretations.shp,hab_class,-1,-1"</Process><Process ToolSource="c:\program files (x86)\arcgis\desktop10.5\ArcToolbox\Toolboxes\Data Management Tools.tbx\CalculateField" Date="20181018" Time="094551">CalculateField Kachemak_Interpretations2 Sub_Grp Mud VB #</Process><Process ToolSource="c:\program files (x86)\arcgis\desktop10.5\ArcToolbox\Toolboxes\Data Management Tools.tbx\CalculateField" Date="20181018" Time="094619">CalculateField Kachemak_Interpretations2 Sub_Grp "Mud" VB #</Process><Process ToolSource="c:\program files (x86)\arcgis\desktop10.5\ArcToolbox\Toolboxes\Data Management Tools.tbx\CalculateField" Date="20181018" Time="094702">CalculateField Kachemak_Interpretations2 CMECS "S1.2.2.5" VB #</Process><Process ToolSource="c:\program files (x86)\arcgis\desktop10.5\ArcToolbox\Toolboxes\Data Management Tools.tbx\CalculateField" Date="20181018" Time="112006">CalculateField Kachemak_Interpretations2 Co_oc_el1 "Zostera marina Herbaceous Vegetation" VB #</Process><Process ToolSource="c:\program files (x86)\arcgis\desktop10.5\ArcToolbox\Toolboxes\Data Management Tools.tbx\CalculateField" Date="20181018" Time="112444">CalculateField Kachemak_Interpretations2 CMECS_1 "2.5.2.1.16" VB #</Process><Process ToolSource="c:\program files (x86)\arcgis\desktop10.5\ArcToolbox\Toolboxes\Data Management Tools.tbx\CalculateField" Date="20181018" Time="113046">CalculateField Kachemak_Interpretations2 Modifier_1 "Percent Cover 70% - 100%" VB #</Process><Process ToolSource="c:\program files (x86)\arcgis\desktop10.5\ArcToolbox\Toolboxes\Data Management Tools.tbx\CalculateField" Date="20181018" Time="141338">CalculateField Kachemak_Interpretations2 CMECS_2 "PC09-PC11" VB #</Process></lineage><itemProps><itemLocation><linkage Sync="TRUE">file://\\NCCOS-S-NCNAS01\Data\Imagery_Data\alaska\BIOMapper\Kachemak_Interpretations2</linkage><protocol Sync="TRUE">Local Area Network</protocol></itemLocation></itemProps><copyHistory><copy source="T:\Imagery_Data\alaska\DVD_Files\Kachemak_Interpretations2" dest="\\NCCOS-S-NCNAS01\Data\Imagery_Data\alaska\BIOMapper\Kachemak_Interpretations2" date="20181015" time="15504200"></copy></copyHistory></DataProperties><ArcGISFormat>1.0</ArcGISFormat></Esri></metadata>
